setup.py
django_mvx_utils.egg-info/PKG-INFO
django_mvx_utils.egg-info/SOURCES.txt
django_mvx_utils.egg-info/dependency_links.txt
django_mvx_utils.egg-info/requires.txt
django_mvx_utils.egg-info/top_level.txt
utils/__init__.py
utils/colors.py
utils/decorators.py
utils/encryption.py
utils/fields.py
utils/middleware.py
utils/slugs.py
utils/update.py
utils/templatetags/__init__.py
utils/templatetags/absoluteurl.py
utils/templatetags/floatcomma.py
utils/templatetags/lines.py
utils/templatetags/math.py
utils/templatetags/negativeparens.py
utils/templatetags/range.py
utils/templatetags/singleline.py
utils/templatetags/split.py
utils/templatetags/urlizeblank.py