Metadata-Version: 1.1
Name: django-mvx-utils
Version: 0.0.1
Summary: Random utils for Django.
Home-page: https://github.com/mvx24/django-mvx-utils
Author: mvx24
Author-email: cram2400@gmail.com
License: MIT
Keywords: django utils views decorators
Platform: UNKNOWN
Classifier: Development Status :: 3 - Alpha
Classifier: Environment :: Console
Classifier: Framework :: Django
Classifier: License :: OSI Approved :: MIT License
Classifier: Operating System :: MacOS :: MacOS X
Classifier: Operating System :: POSIX
Classifier: Operating System :: Unix
Classifier: Programming Language :: Python :: 2.7
Classifier: Programming Language :: Python :: 2 :: Only
Classifier: Topic :: Database
Classifier: Topic :: Software Development :: Libraries :: Python Modules
